clin28tools
