Metadata-Version: 1.1
Name: clin28tools
Version: 0.1.5
Summary: Scripts for the CLIN28 Shared Task on spelling correction
Home-page: https://github.com/LanguageMachines/CLIN28_ST_spelling_correction
Author: Maarten van Gompel, Merijn Beeksma, Florian Kunneman
Author-email: proycon@anaproy.nl
License: GPL
Keywords: nlp computational_linguistics spelling_correction
Platform: UNKNOWN
Classifier: Development Status :: 4 - Beta
Classifier: Topic :: Text Processing :: Linguistic
Classifier: Programming Language :: Python :: 3.4
Classifier: Programming Language :: Python :: 3.5
Classifier: Programming Language :: Python :: 3.6
Classifier: Operating System :: POSIX
Classifier: Intended Audience :: Science/Research
Classifier: License :: OSI Approved :: GNU General Public License v3 (GPLv3)
